{
  "version": 1,
  "levelCap": 65,
  "damageBonus1H": {
    "_comment": "Warrior only, level 28+. bonus = 1 + (level - 28) / 3."
  },
  "damageBonus2H": {
    "_comment": "Warrior 2H: formula in code. delay 1-70, level 28-65."
  },
  "classes": {
    "Warrior": {
      "skills": { "offense": 252, "defense": 252, "doubleAttack": 252, "dualWield": 245, "1HSlash": 250, "2HSlash": 250, "1HBlunt": 250, "2HBlunt": 250, "1HPiercing": 250, "2HPiercing": 250 },
      "str": 280,
      "dex": 280,
      "agi": 280,
      "aas": [
        { "id": "Ferocity", "label": "Ferocity", "bonuses": { "DoubleAttackChance": 9 } },
        { "id": "CombatFury", "label": "Combat Fury", "bonuses": { "CriticalHitChance": 75 } },
        { "id": "FuryOfTheAges", "label": "Fury of the Ages", "bonuses": { "CriticalHitChance": 150 } },
        { "id": "PlanarPower", "label": "Planar Power", "bonuses": { "StatBonus": 25 } },
        { "id": "Flurry", "label": "Flurry", "bonuses": { "FlurryChance": 30 } },
        { "id": "RagingFlurry", "label": "Raging Flurry", "bonuses": { "FlurryChance": 7 } },
        { "id": "Ambidexterity", "label": "Ambidexterity", "bonuses": { "Ambidexterity": 32 } },
        { "id": "CombatAgility", "label": "Combat Agility", "bonuses": { "CombatAgility": 10 } },
        { "id": "DoubleRiposte", "label": "Double Riposte", "bonuses": { "GiveDoubleRiposte0": 50 } },
        { "id": "PunishingBlade", "label": "Punishing Blade", "bonuses": { "ExtraAttackChance": 8 } },
        { "id": "Strikethrough", "label": "Tactical Mastery (Strikethrough)", "bonuses": { "StrikeThrough": 45 } }
      ]
    },
    "Rogue": {
      "skills": { "offense": 252, "defense": 252, "doubleAttack": 252, "dualWield": 245, "1HPiercing": 250, "backstab": 252 },
      "str": 280,
      "dex": 280,
      "agi": 280,
      "aas": [
        { "id": "CombatFury", "label": "Combat Fury", "bonuses": { "CriticalHitChance": 75 } },
        { "id": "FuryOfTheAges", "label": "Fury of the Ages", "bonuses": { "CriticalHitChance": 150 } },
        { "id": "PlanarPower", "label": "Planar Power", "bonuses": { "StatBonus": 25 } },
        { "id": "Ambidexterity", "label": "Ambidexterity", "bonuses": { "Ambidexterity": 32 } },
        { "id": "CombatAgility", "label": "Combat Agility", "bonuses": { "CombatAgility": 10 } },
        { "id": "DoubleRiposte", "label": "Double Riposte", "bonuses": { "GiveDoubleRiposte0": 50 } },
        { "id": "ChaoticStab", "label": "Chaotic Stab", "bonuses": { "FrontalBackstabMinDmg": 1 } }
      ]
    },
    "Monk": {
      "skills": { "offense": 252, "defense": 252, "doubleAttack": 252, "dualWield": 252, "handToHand": 252, "1HBlunt": 252, "2HBlunt": 252, "kick": 252 },
      "str": 280,
      "dex": 280,
      "agi": 280,
      "aas": [
        { "id": "CombatFury", "label": "Combat Fury", "bonuses": { "CriticalHitChance": 75 } },
        { "id": "FuryOfTheAges", "label": "Fury of the Ages", "bonuses": { "CriticalHitChance": 150 } },
        { "id": "PlanarPower", "label": "Planar Power", "bonuses": { "StatBonus": 25 } },
        { "id": "Ambidexterity", "label": "Ambidexterity", "bonuses": { "Ambidexterity": 32 } },
        { "id": "CombatAgility", "label": "Combat Agility", "bonuses": { "CombatAgility": 10 } },
        { "id": "ReturnKick", "label": "Return Kick", "bonuses": { "RiposteChance": 60 } },
        { "id": "DoubleRiposte", "label": "Double Riposte", "bonuses": { "GiveDoubleRiposte0": 50 } },
        { "id": "PunishingBlade", "label": "Punishing Blade", "bonuses": { "ExtraAttackChance": 8 } },
        { "id": "TechniqueOfMasterWu", "label": "Technique of Master Wu", "bonuses": { "DoubleSpecialAttack": 100 } }
      ]
    },
    "Ranger": {
      "skills": { "offense": 252, "defense": 240, "doubleAttack": 252, "dualWield": 252, "archery": 252, "1HSlash": 252, "2HSlash": 252 },
      "str": 280,
      "dex": 280,
      "agi": 280,
      "aas": [
        { "id": "ArcheryMastery", "label": "Archery Mastery", "bonuses": { "ArcheryDamageModifier": 100 } },
        { "id": "CombatFury", "label": "Combat Fury", "bonuses": { "CriticalHitChance": 75 } },
        { "id": "FuryOfTheAges", "label": "Fury of the Ages", "bonuses": { "CriticalHitChance": 150 } },
        { "id": "PlanarPower", "label": "Planar Power", "bonuses": { "StatBonus": 25 } },
        { "id": "Ambidexterity", "label": "Ambidexterity", "bonuses": { "Ambidexterity": 32 } },
        { "id": "CombatAgility", "label": "Combat Agility", "bonuses": { "CombatAgility": 10 } },
        { "id": "DoubleRiposte", "label": "Double Riposte", "bonuses": { "GiveDoubleRiposte0": 50 } },
        { "id": "PunishingBlade", "label": "Punishing Blade", "bonuses": { "ExtraAttackChance": 8 } }
      ]
    },
    "Paladin": {
      "skills": { "offense": 225, "defense": 225, "doubleAttack": 225, "dualWield": 225, "1HSlash": 225, "2HSlash": 225, "1HBlunt": 225 },
      "str": 280,
      "dex": 280,
      "agi": 280,
      "aas": [
        { "id": "KnightsAdvantage", "label": "Knight's Advantage", "bonuses": { "DoubleAttackChance": 9 } },
        { "id": "CombatFury", "label": "Combat Fury", "bonuses": { "CriticalHitChance": 75 } },
        { "id": "FuryOfTheAges", "label": "Fury of the Ages", "bonuses": { "CriticalHitChance": 150 } },
        { "id": "PlanarPower", "label": "Planar Power", "bonuses": { "StatBonus": 25 } },
        { "id": "Ambidexterity", "label": "Ambidexterity", "bonuses": { "Ambidexterity": 32 } },
        { "id": "CombatAgility", "label": "Combat Agility", "bonuses": { "CombatAgility": 10 } },
        { "id": "DoubleRiposte", "label": "Double Riposte", "bonuses": { "GiveDoubleRiposte0": 50 } },
        { "id": "PunishingBlade", "label": "Punishing Blade", "bonuses": { "ExtraAttackChance": 8 } },
        { "id": "SpeedOfTheKnight", "label": "Speed of the Knight", "bonuses": { "ExtraAttackChance": 8 } }
      ]
    },
    "Shadow Knight": {
      "skills": { "offense": 225, "defense": 225, "doubleAttack": 225, "dualWield": 225, "1HSlash": 225, "2HSlash": 225, "1HPiercing": 225 },
      "str": 280,
      "dex": 280,
      "agi": 280,
      "aas": [
        { "id": "KnightsAdvantage", "label": "Knight's Advantage", "bonuses": { "DoubleAttackChance": 9 } },
        { "id": "CombatFury", "label": "Combat Fury", "bonuses": { "CriticalHitChance": 75 } },
        { "id": "FuryOfTheAges", "label": "Fury of the Ages", "bonuses": { "CriticalHitChance": 150 } },
        { "id": "PlanarPower", "label": "Planar Power", "bonuses": { "StatBonus": 25 } },
        { "id": "Ambidexterity", "label": "Ambidexterity", "bonuses": { "Ambidexterity": 32 } },
        { "id": "CombatAgility", "label": "Combat Agility", "bonuses": { "CombatAgility": 10 } },
        { "id": "DoubleRiposte", "label": "Double Riposte", "bonuses": { "GiveDoubleRiposte0": 50 } },
        { "id": "PunishingBlade", "label": "Punishing Blade", "bonuses": { "ExtraAttackChance": 8 } },
        { "id": "SpeedOfTheKnight", "label": "Speed of the Knight", "bonuses": { "ExtraAttackChance": 8 } }
      ]
    },
    "Bard": {
      "skills": { "offense": 252, "defense": 252, "doubleAttack": 0, "dualWield": 245, "1HSlash": 250, "1HBlunt": 250, "2HBlunt": 250, "1HPiercing": 250 },
      "str": 280,
      "dex": 280,
      "agi": 280,
      "aas": [
        { "id": "CombatFury", "label": "Combat Fury", "bonuses": { "CriticalHitChance": 75 } },
        { "id": "FuryOfTheAges", "label": "Fury of the Ages", "bonuses": { "CriticalHitChance": 150 } },
        { "id": "PlanarPower", "label": "Planar Power", "bonuses": { "StatBonus": 25 } },
        { "id": "Ambidexterity", "label": "Ambidexterity", "bonuses": { "Ambidexterity": 32 } },
        { "id": "CombatAgility", "label": "Combat Agility", "bonuses": { "CombatAgility": 10 } }
      ]
    },
    "Beastlord": {
      "skills": { "offense": 252, "defense": 240, "doubleAttack": 0, "dualWield": 245, "handToHand": 250, "1HBlunt": 225, "2HBlunt": 225 },
      "str": 280,
      "dex": 280,
      "agi": 280,
      "aas": [
        { "id": "BestialFrenzy", "label": "Bestial Frenzy", "bonuses": { "GiveDoubleAttack": 15 } },
        { "id": "Ambidexterity", "label": "Ambidexterity", "bonuses": { "Ambidexterity": 32 } },
        { "id": "CombatFury", "label": "Combat Fury", "bonuses": { "CriticalHitChance": 75 } },
        { "id": "FuryOfTheAges", "label": "Fury of the Ages", "bonuses": { "CriticalHitChance": 150 } },
        { "id": "PlanarPower", "label": "Planar Power", "bonuses": { "StatBonus": 25 } }
      ]
    }
  }
}
